cloud_manager/__init__.py
cloud_manager/ncloud.py
cloud_manager-0.1.3.dist-info/LICENSE
cloud_manager-0.1.3.dist-info/METADATA
cloud_manager-0.1.3.dist-info/WHEEL
cloud_manager-0.1.3.dist-info/top_level.txt
cloud_manager-0.1.3.dist-info/RECORD
