Metadata-Version: 2.1
Name: cloud-manager
Version: 0.1.3
Summary: Package for managing cloud service using python. NCloud, AWS, AZURE, GCP
Home-page: https://github.com/hoosiki/cloud_manager.git
Author: Junsang Park
Author-email: publichey@gmail.com
License: BSD
Download-URL: https://github.com/hoosiki/cloud_manager/blob/master/dist/cloud_manager-0.1.3.tar.gz
Platform: UNKNOWN
Requires-Dist: pandas
Requires-Dist: config2
Requires-Dist: notion
Requires-Dist: notion-as-db
Requires-Dist: ncloud-server
